shaleprotocol/__init__.py
shaleprotocol/__main__.py
shaleprotocol-0.0.1.dist-info/LICENSE.txt
shaleprotocol-0.0.1.dist-info/METADATA
shaleprotocol-0.0.1.dist-info/WHEEL
shaleprotocol-0.0.1.dist-info/entry_points.txt
shaleprotocol-0.0.1.dist-info/top_level.txt
shaleprotocol-0.0.1.dist-info/RECORD
